README.md
datek_jaipur/__init__.py
datek_jaipur/application/__init__.py
datek_jaipur/application/adapters/__init__.py
datek_jaipur/application/adapters/base.py
datek_jaipur/application/adapters/console/__init__.py
datek_jaipur/application/adapters/console/adapter.py
datek_jaipur/application/adapters/console/constants.py
datek_jaipur/application/adapters/console/errors.py
datek_jaipur/application/adapters/console/formatters.py
datek_jaipur/application/console.py
datek_jaipur/application/state_machine/__init__.py
datek_jaipur/application/state_machine/fsm.py
datek_jaipur/application/state_machine/scope.py
datek_jaipur/application/state_machine/states.py
datek_jaipur/domain/__init__.py
datek_jaipur/domain/compound_types/__init__.py
datek_jaipur/domain/compound_types/card.py
datek_jaipur/domain/compound_types/coin.py
datek_jaipur/domain/compound_types/game.py
datek_jaipur/domain/compound_types/goods.py
datek_jaipur/domain/compound_types/player.py
datek_jaipur/domain/compound_types/turn.py
datek_jaipur/domain/constants.py
datek_jaipur/domain/errors/__init__.py
datek_jaipur/domain/errors/game_created.py
datek_jaipur/domain/errors/goods_bought.py
datek_jaipur/domain/errors/goods_sold.py
datek_jaipur/domain/errors/goods_traded.py
datek_jaipur/domain/errors/player_created.py
datek_jaipur/domain/events/__init__.py
datek_jaipur/domain/events/all_card_sets_created.py
datek_jaipur/domain/events/all_coin_sets_created.py
datek_jaipur/domain/events/card_set_created.py
datek_jaipur/domain/events/game_created.py
datek_jaipur/domain/events/goods_bought.py
datek_jaipur/domain/events/goods_sold.py
datek_jaipur/domain/events/goods_traded.py
datek_jaipur/domain/events/player_created.py
datek_jaipur/domain/simple_types.py
datek_jaipur/domain/utils.py
datek_jaipur/errors.py
datek_jaipur/utils.py
datek_jaipur-0.1.1.dist-info/entry_points.txt
datek_jaipur-0.1.1.dist-info/LICENSE
datek_jaipur-0.1.1.dist-info/WHEEL
datek_jaipur-0.1.1.dist-info/METADATA
datek_jaipur-0.1.1.dist-info/RECORD
