Metadata-Version: 2.1
Name: datek-jaipur
Version: 0.1.1
Summary: Implementation of Jaipur board game's logic
Home-page: https://github.com/DAtek/datek-jaipur
License: MIT
Author: Attila Dudas
Author-email: dudasa7@gmail.com
Requires-Python: >=3.10,<4.0
Classifier: License :: OSI Approved :: MIT License
Classifier: Programming Language :: Python :: 3
Classifier: Programming Language :: Python :: 3.10
Requires-Dist: datek-async-fsm (>=0.2.0,<0.3.0)
Project-URL: Repository, https://github.com/DAtek/datek-jaipur
